pover/__init__.py
pover/core.py
pover/tests/__init__.py
pover/tests/tests.py
pover-0.0.1.dist-info/LICENSE
pover-0.0.1.dist-info/METADATA
pover-0.0.1.dist-info/WHEEL
pover-0.0.1.dist-info/top_level.txt
pover-0.0.1.dist-info/RECORD
