Metadata-Version: 2.1
Name: pover
Version: 0.0.1
Summary: Python Overloading Methods
Home-page: https://github.com/idf/pover
Author: Daniel D. Zhang
Author-email: dzhang.idf@gmail.com
License: GNU GENERAL PUBLIC LICENSE
Platform: UNKNOWN
